pystuff/__init__.py
pystuff/test.py
PyStuff2302-3.0.0.dist-info/LICENSE
PyStuff2302-3.0.0.dist-info/METADATA
PyStuff2302-3.0.0.dist-info/WHEEL
PyStuff2302-3.0.0.dist-info/entry_points.txt
PyStuff2302-3.0.0.dist-info/top_level.txt
PyStuff2302-3.0.0.dist-info/RECORD
