Metadata-Version: 2.1
Name: PyStuff2302
Version: 3.0.0
Summary: Demo Package for testing.
Home-page: https://github.com/ardada2468/pystuff
Author: Arnav Dadarya
Author-email: ardada2468@gmail.com
License: MIT
Keywords: arnav dadarya
Classifier: Programming Language :: Python :: 3
Classifier: License :: OSI Approved :: MIT License
Classifier: Operating System :: OS Independent
License-File: LICENSE
Requires-Dist: requests (==2.27.1)
